{
	"drivers": [
		{
			"year": "1979",
			"overall_position_scoring": {
				"1": "20",
				"2": "15",
				"3": "12",
				"4": "10",
				"5": "8",
				"6": "6",
				"7": "4",
				"8": "3",
				"9": "2",
				"10": "1"
			}
		},
		{
			"year": "1997",
			"overall_position_scoring": {
				"1": "10",
				"2": "6",
				"3": "4",
				"4": "3",
				"5": "2",
				"6": "1"
			}
		},
		{
			"year": "2003",
			"overall_position_scoring": {
				"1": "10",
				"2": "8",
				"3": "8",
				"4": "5",
				"5": "4",
				"6": "3",
				"7": "2",
				"8": "1"
			}
		},
		{
			"year": "2010",
			"overall_position_scoring": {
				"1": "25",
				"2": "18",
				"3": "15",
				"4": "12",
				"5": "10",
				"6": "8",
				"7": "6",
				"8": "4",
				"9": "2",
				"10": "1"
			}
		}
	]
}